[
  {
    "id": "wuppertal",
    "name": "Wuppertal",
    "aliases": [
      "Ennepetal",
      "Schwelm",
      "Gevelsberg"
    ],
    "latitude": 51.2562,
    "longitude": 7.1508,
    "radiusMeters": 18000,
    "transitRadar": [
      {
        "providerID": "wsw-wuppertal",
        "features": [
          "liveVehicles",
          "realtimeDelay"
        ],
        "statusMessage": "Live-Radar für Wuppertal"
      },
      {
        "adapter": "dbRegioBusNRW",
        "region": {
          "minimumLongitude": 6.93,
          "minimumLatitude": 51.2,
          "maximumLongitude": 7.3,
          "maximumLatitude": 51.4
        }
      },
      {
        "adapter": "vrrEFA",
        "efaPath": "static03"
      }
    ]
  },
  {
    "id": "berlin",
    "name": "Berlin",
    "aliases": [],
    "latitude": 52.52,
    "longitude": 13.405,
    "radiusMeters": 30000,
    "transitRadar": {
      "adapter": "vbb",
      "isEnabled": true,
      "supportsDepartures": true,
      "region": {
        "minimumLongitude": 13.0884,
        "minimumLatitude": 52.3383,
        "maximumLongitude": 13.7612,
        "maximumLatitude": 52.6755
      }
    }
  },
  {
    "id": "potsdam-12054000",
    "name": "Potsdam",
    "aliases": [],
    "latitude": 52.3906,
    "longitude": 13.0645,
    "radiusMeters": 18000,
    "transitRadar": {
      "adapter": "vbb",
      "isEnabled": true,
      "supportsDepartures": true,
      "region": {
        "minimumLongitude": 12.87,
        "minimumLatitude": 52.28,
        "maximumLongitude": 13.27,
        "maximumLatitude": 52.52
      }
    }
  },
  {
    "id": "brandenburg-an-der-havel-12051000",
    "name": "Brandenburg an der Havel",
    "aliases": [],
    "latitude": 52.4125,
    "longitude": 12.5316,
    "radiusMeters": 16000,
    "transitRadar": {
      "adapter": "vbb",
      "isEnabled": true,
      "supportsDepartures": true,
      "region": {
        "minimumLongitude": 12.38,
        "minimumLatitude": 52.31,
        "maximumLongitude": 12.68,
        "maximumLatitude": 52.51
      }
    }
  },
  {
    "id": "cottbus",
    "name": "Cottbus",
    "aliases": [
      "Chóśebuz"
    ],
    "latitude": 51.7563,
    "longitude": 14.3329,
    "radiusMeters": 25000,
    "transitRadar": {
      "adapter": "vbb",
      "isEnabled": true,
      "region": {
        "minimumLongitude": 14.05,
        "minimumLatitude": 51.6,
        "maximumLongitude": 14.62,
        "maximumLatitude": 51.92
      }
    }
  },
  {
    "id": "darmstadt",
    "name": "Darmstadt",
    "aliases": [],
    "latitude": 49.8728,
    "longitude": 8.6512,
    "radiusMeters": 18000,
    "transitRadar": [
      {
        "adapter": "ivantoMQTT",
        "agency": "heag",
        "isEnabled": true,
        "region": {
          "minimumLongitude": 8.35,
          "minimumLatitude": 49.6,
          "maximumLongitude": 9.05,
          "maximumLatitude": 50.2
        }
      },
      {"adapter":"rmvHafas","isEnabled":true,"supportsDepartures":true,"supportsLiveVehicles":false,"supportsRealtimeDelay":true,"statusMessage":"RMV-Abfahrten"}
    ]
  },
  {
    "id": "hamburg",
    "name": "Hamburg",
    "aliases": [],
    "latitude": 53.5511,
    "longitude": 9.9937,
    "radiusMeters": 25000,
    "transitRadar": {
      "adapter": "hvvEFA",
      "efaPath": "efa",
      "supportsLiveVehicles": true,
      "radarStops": [
        {
          "id": "28510950",
          "latitude": 53.552753,
          "longitude": 10.007924
        },
        {
          "id": "28510002",
          "latitude": 53.551904,
          "longitude": 10.01034
        },
        {
          "id": "28510905",
          "latitude": 53.554092,
          "longitude": 10.005957
        },
        {
          "id": "28510906",
          "latitude": 53.552027,
          "longitude": 10.009469
        },
        {
          "id": "28510051",
          "latitude": 53.552924,
          "longitude": 10.008553
        },
        {
          "id": "28500079",
          "latitude": 53.55326,
          "longitude": 9.935412
        },
        {
          "id": "28511950",
          "latitude": 53.552748,
          "longitude": 9.994907
        },
        {
          "id": "28560902",
          "latitude": 53.571662,
          "longitude": 10.066323
        },
        {
          "id": "28549950",
          "latitude": 53.456888,
          "longitude": 9.991314
        }
      ],
      "region": {
        "minimumLongitude": 9.72,
        "minimumLatitude": 53.38,
        "maximumLongitude": 10.32,
        "maximumLatitude": 53.72
      }
    }
  },
  {
    "id": "norderstedt-01060063",
    "name": "Norderstedt",
    "aliases": [],
    "latitude": 53.7064,
    "longitude": 10.0103,
    "radiusMeters": 14000,
    "transitRadar": {
      "adapter": "hvvEFA",
      "efaPath": "efa",
      "supportsLiveVehicles": true,
      "radarStops": [
        {
          "id": "28536071",
          "latitude": 53.706799,
          "longitude": 9.99223
        }
      ],
      "region": {
        "minimumLongitude": 9.88,
        "minimumLatitude": 53.62,
        "maximumLongitude": 10.14,
        "maximumLatitude": 53.79
      }
    }
  },
  {
    "id": "lueneburg-03355022",
    "name": "Lüneburg",
    "aliases": [
      "Lueneburg"
    ],
    "latitude": 53.2464,
    "longitude": 10.4115,
    "radiusMeters": 14000,
    "transitRadar": {
      "adapter": "hvvEFA",
      "efaPath": "efa",
      "supportsLiveVehicles": true,
      "radarStops": [
        {
          "id": "28525080",
          "latitude": 53.248701,
          "longitude": 10.419083
        }
      ],
      "region": {
        "minimumLongitude": 10.28,
        "minimumLatitude": 53.16,
        "maximumLongitude": 10.55,
        "maximumLatitude": 53.34
      }
    }
  },
  {
    "id": "stade-03359038",
    "name": "Stade",
    "aliases": [],
    "latitude": 53.601,
    "longitude": 9.4767,
    "radiusMeters": 14000,
    "transitRadar": {
      "adapter": "hvvEFA",
      "efaPath": "efa",
      "supportsLiveVehicles": true,
      "radarStops": [
        {
          "id": "28535080",
          "latitude": 53.596508,
          "longitude": 9.476651
        },
        {
          "id": "28500048",
          "latitude": 53.596166,
          "longitude": 9.477127
        },
        {
          "id": "28535012",
          "latitude": 53.600005,
          "longitude": 9.474531
        },
        {
          "id": "28535180",
          "latitude": 53.601583,
          "longitude": 9.471073
        },
        {
          "id": "28535200",
          "latitude": 53.603118,
          "longitude": 9.467902
        },
        {
          "id": "28533419",
          "latitude": 53.606438,
          "longitude": 9.467048
        },
        {
          "id": "28533403",
          "latitude": 53.598448,
          "longitude": 9.443405
        },
        {
          "id": "28535049",
          "latitude": 53.588979,
          "longitude": 9.486156
        }
      ],
      "region": {
        "minimumLongitude": 9.32,
        "minimumLatitude": 53.5,
        "maximumLongitude": 9.62,
        "maximumLatitude": 53.7
      }
    }
  },
  {
    "id": "buxtehude-03359010",
    "name": "Buxtehude",
    "aliases": [],
    "latitude": 53.467,
    "longitude": 9.6869,
    "radiusMeters": 14000,
    "transitRadar": {
      "adapter": "hvvEFA",
      "efaPath": "efa",
      "supportsLiveVehicles": true,
      "radarStops": [
        {
          "id": "28551989",
          "latitude": 53.470546,
          "longitude": 9.688061
        },
        {
          "id": "28545010",
          "latitude": 53.470102,
          "longitude": 9.688672
        },
        {
          "id": "28545011",
          "latitude": 53.470568,
          "longitude": 9.689714
        },
        {
          "id": "28545014",
          "latitude": 53.470814,
          "longitude": 9.690378
        },
        {
          "id": "28545050",
          "latitude": 53.474102,
          "longitude": 9.697843
        },
        {
          "id": "28545036",
          "latitude": 53.46206,
          "longitude": 9.67791
        },
        {
          "id": "28545017",
          "latitude": 53.46045,
          "longitude": 9.66519
        },
        {
          "id": "28545028",
          "latitude": 53.47754,
          "longitude": 9.706701
        },
        {
          "id": "28545039",
          "latitude": 53.463996,
          "longitude": 9.693568
        }
      ],
      "region": {
        "minimumLongitude": 9.55,
        "minimumLatitude": 53.38,
        "maximumLongitude": 9.82,
        "maximumLatitude": 53.55
      }
    }
  },
  {
    "id": "muenchen",
    "name": "München",
    "aliases": [
      "Muenchen",
      "Munich"
    ],
    "latitude": 48.1351,
    "longitude": 11.582,
    "radiusMeters": 23000,
    "transitRadar": {
      "adapter": "mvvEFA",
      "efaPath": "ng",
      "supportsCoordinateCatalog": false,
      "supportsLiveVehicles": true,
      "radarStops": [
        {
          "id": "91000100",
          "latitude": 48.1407,
          "longitude": 11.5654
        },
        {
          "id": "91000002",
          "latitude": 48.1374,
          "longitude": 11.5753
        },
        {
          "id": "91000050",
          "latitude": 48.1341,
          "longitude": 11.5657
        },
        {
          "id": "91000500",
          "latitude": 48.1614,
          "longitude": 11.5864
        },
        {
          "id": "91000300",
          "latitude": 48.1276,
          "longitude": 11.6033
        }
      ],
      "region": {
        "minimumLongitude": 11.35,
        "minimumLatitude": 48.05,
        "maximumLongitude": 11.7,
        "maximumLatitude": 48.22
      }
    }
  },
  {
    "id": "nurnberg",
    "name": "Nürnberg",
    "aliases": [
      "Nuernberg",
      "Nuremberg"
    ],
    "latitude": 49.4521,
    "longitude": 11.0767,
    "radiusMeters": 18000,
    "transitRadar": {
      "adapter": "vagPuls",
      "isEnabled": false,
      "region": {
        "minimumLongitude": 10.98,
        "minimumLatitude": 49.33,
        "maximumLongitude": 11.28,
        "maximumLatitude": 49.59
      }
    }
  },
  {
    "id": "koln",
    "name": "Köln",
    "aliases": [
      "Koeln",
      "Cologne"
    ],
    "latitude": 50.9375,
    "longitude": 6.9603,
    "radiusMeters": 18000,
    "transitRadar": [
      {
        "adapter": "vrs",
        "providerID": "vrs-koln",
        "features": [
          "liveVehicles",
          "realtimeDepartures",
          "firstDepartures",
          "stopLookup",
          "realtimeDelay"
        ],
        "statusMessage": "Live-Abfahrten für Köln",
        "triasURL": "https://api.vrs.de/v1/trias",
        "gtfsRTURL": "https://gtfs-rt-test.vrs.de:4443/buffer/tripUpdate.buf",
        "requestorRef": "HalteWecker",
        "region": {
          "minimumLongitude": 6.7,
          "minimumLatitude": 50.8,
          "maximumLongitude": 7.2,
          "maximumLatitude": 51.1
        },
        "assURL": "https://apitest.vrs.de:4443/v1/ass",
        "supportsLiveVehicles": true
      }
    ]
  },
  {
    "id": "dusseldorf",
    "name": "Düsseldorf",
    "aliases": [
      "Duesseldorf"
    ],
    "latitude": 51.2277,
    "longitude": 6.7735,
    "radiusMeters": 18000,
    "transitRadar": [
      {
        "providerID": "rheinbahn-duesseldorf",
        "features": [
          "realtimeDepartures",
          "firstDepartures",
          "stopLookup",
          "realtimeDelay"
        ],
        "statusMessage": "Live-Abfahrten für Düsseldorf"
      },
      {
        "adapter": "vrrEFA",
        "efaPath": "static03",
        "supportsDepartures": false,
        "supportsLiveVehicles": true,
        "radarStops": [
          {
            "id": "20018235",
            "latitude": 51.220253,
            "longitude": 6.792997
          },
          {
            "id": "20018036",
            "latitude": 51.2264,
            "longitude": 6.776828
          },
          {
            "id": "20018249",
            "latitude": 51.208195,
            "longitude": 6.776891
          },
          {
            "id": "20018029",
            "latitude": 51.234993,
            "longitude": 6.778121
          },
          {
            "id": "20018263",
            "latitude": 51.161945,
            "longitude": 6.878194
          },
          {
            "id": "20018259",
            "latitude": 51.2017,
            "longitude": 6.837266
          },
          {
            "id": "20018266",
            "latitude": 51.17526,
            "longitude": 6.832945
          },
          {
            "id": "20018210",
            "latitude": 51.26219,
            "longitude": 6.810586
          },
          {
            "id": "20018206",
            "latitude": 51.27658,
            "longitude": 6.786808
          },
          {
            "id": "20018525",
            "latitude": 51.253414,
            "longitude": 6.771806
          },
          {
            "id": "20018748",
            "latitude": 51.1801,
            "longitude": 6.862105
          },
          {
            "id": "20018273",
            "latitude": 51.23158,
            "longitude": 6.748019
          },
          {
            "id": "20018261",
            "latitude": 51.199043,
            "longitude": 6.846115
          }
        ],
        "region": {
          "minimumLongitude": 6.6,
          "minimumLatitude": 51.1,
          "maximumLongitude": 6.95,
          "maximumLatitude": 51.35
        }
      }
    ]
  },
  {
    "id": "krefeld",
    "name": "Krefeld",
    "aliases": [],
    "latitude": 51.3388,
    "longitude": 6.5853,
    "radiusMeters": 18000,
    "transitRadar": {
      "adapter": "vrrEFA",
      "efaPath": "static03",
      "supportsDepartures": true,
      "supportsLiveVehicles": true,
      "autoRadarStops": true,
      "statusMessage": "Live-Radar (geschätzt) und Live-Abfahrten für Krefeld"
    }
  },
  {
    "id": "essen",
    "name": "Essen",
    "aliases": [],
    "latitude": 51.4556,
    "longitude": 7.0116,
    "radiusMeters": 18000,
    "transitRadar": [
      {
        "adapter": "dbRegioBusNRW",
        "region": {
          "minimumLongitude": 6.45,
          "minimumLatitude": 51.2,
          "maximumLongitude": 7.45,
          "maximumLatitude": 51.65
        }
      },
      {
        "adapter": "ivantoMQTT",
        "agency": "evag",
        "isEnabled": true,
        "region": {
          "minimumLongitude": 6.72,
          "minimumLatitude": 51.28,
          "maximumLongitude": 7.25,
          "maximumLatitude": 51.58
        }
      },
      {
        "adapter": "vrrEFA",
        "efaPath": "static03",
        "supportsDepartures": true,
        "supportsLiveVehicles": false,
        "statusMessage": "Live-Abfahrten für Essen"
      }
    ]
  },
  {
    "id": "mulheim-an-der-ruhr",
    "name": "Mülheim an der Ruhr",
    "aliases": [
      "Muelheim an der Ruhr"
    ],
    "latitude": 51.4275,
    "longitude": 6.8825,
    "radiusMeters": 14000,
    "transitRadar": [
      {
        "adapter": "ivantoMQTT",
        "agency": "evag",
        "isEnabled": true,
        "region": {
          "minimumLongitude": 6.72,
          "minimumLatitude": 51.28,
          "maximumLongitude": 7.25,
          "maximumLatitude": 51.58
        }
      },
      {
        "adapter": "vrrEFA",
        "efaPath": "static03",
        "supportsDepartures": true,
        "supportsLiveVehicles": false,
        "statusMessage": "Live-Abfahrten für Mülheim an der Ruhr"
      }
    ]
  },
  {
    "id": "bochum",
    "name": "Bochum",
    "aliases": [],
    "latitude": 51.4818,
    "longitude": 7.2162,
    "radiusMeters": 18000,
    "transitRadar": {
      "adapter": "vrrEFA",
      "efaPath": "static03",
      "supportsDepartures": true,
      "supportsLiveVehicles": true,
      "autoRadarStops": true,
      "statusMessage": "Live-Radar (geschätzt) und Live-Abfahrten für Bochum"
    }
  },
  {
    "id": "gelsenkirchen",
    "name": "Gelsenkirchen",
    "aliases": [],
    "latitude": 51.5177,
    "longitude": 7.0857,
    "radiusMeters": 16000,
    "transitRadar": {
      "adapter": "vrrEFA",
      "efaPath": "static03",
      "supportsDepartures": true,
      "supportsLiveVehicles": true,
      "autoRadarStops": true,
      "statusMessage": "Live-Radar (geschätzt) und Live-Abfahrten für Gelsenkirchen"
    }
  },
  {
    "id": "bottrop",
    "name": "Bottrop",
    "aliases": [],
    "latitude": 51.5292,
    "longitude": 6.9447,
    "radiusMeters": 14000,
    "transitRadar": {
      "adapter": "vrrEFA",
      "efaPath": "static03",
      "supportsDepartures": true,
      "supportsLiveVehicles": true,
      "autoRadarStops": true,
      "statusMessage": "Live-Radar (geschätzt) und Live-Abfahrten für Bottrop"
    }
  },
  {
    "id": "herne",
    "name": "Herne",
    "aliases": [],
    "latitude": 51.5389,
    "longitude": 7.2257,
    "radiusMeters": 12000,
    "transitRadar": {
      "adapter": "vrrEFA",
      "efaPath": "static03",
      "supportsDepartures": true,
      "supportsLiveVehicles": true,
      "autoRadarStops": true,
      "statusMessage": "Live-Radar (geschätzt) und Live-Abfahrten für Herne"
    }
  },
  {
    "id": "oberhausen",
    "name": "Oberhausen",
    "aliases": [],
    "latitude": 51.4963,
    "longitude": 6.8517,
    "radiusMeters": 14000,
    "transitRadar": {
      "adapter": "vrrEFA",
      "efaPath": "static03",
      "supportsDepartures": true,
      "supportsLiveVehicles": true,
      "autoRadarStops": true,
      "statusMessage": "Live-Radar (geschätzt) und Live-Abfahrten für Oberhausen"
    }
  },
  {
    "id": "duisburg",
    "name": "Duisburg",
    "aliases": [],
    "latitude": 51.4344,
    "longitude": 6.7623,
    "radiusMeters": 18000,
    "transitRadar": [
      {
        "adapter": "dbRegioBusNRW",
        "region": {
          "minimumLongitude": 6.45,
          "minimumLatitude": 51.2,
          "maximumLongitude": 7.45,
          "maximumLatitude": 51.65
        }
      },
      {
        "adapter": "vrrEFA",
        "efaPath": "static03",
        "supportsLiveVehicles": true,
        "radarStops": [
          {
            "id": "20016032",
            "latitude": 51.430454,
            "longitude": 6.774528
          },
          {
            "id": "20016031",
            "latitude": 51.433086,
            "longitude": 6.767934
          },
          {
            "id": "20016009",
            "latitude": 51.5021,
            "longitude": 6.757172
          },
          {
            "id": "20016056",
            "latitude": 51.4662,
            "longitude": 6.7796
          },
          {
            "id": "20016265",
            "latitude": 51.410343,
            "longitude": 6.720066
          }
        ],
        "region": {
          "minimumLongitude": 6.55,
          "minimumLatitude": 51.3,
          "maximumLongitude": 6.95,
          "maximumLatitude": 51.56
        }
      }
    ]
  },
  {
    "id": "hagen-05914000",
    "name": "Hagen",
    "aliases": [],
    "latitude": 51.3671,
    "longitude": 7.4633,
    "radiusMeters": 18000,
    "transitRadar": {
      "adapter": "vrrEFA",
      "efaPath": "static03",
      "supportsLiveVehicles": true,
      "radarStops": [
        {
          "id": "20002007",
          "latitude": 51.361965,
          "longitude": 7.461802
        },
        {
          "id": "20002003",
          "latitude": 51.359264,
          "longitude": 7.472842
        },
        {
          "id": "20002410",
          "latitude": 51.358974,
          "longitude": 7.475872
        },
        {
          "id": "20002020",
          "latitude": 51.39558,
          "longitude": 7.469348
        },
        {
          "id": "20002037",
          "latitude": 51.347385,
          "longitude": 7.421584
        }
      ],
      "region": {
        "minimumLongitude": 7.3,
        "minimumLatitude": 51.25,
        "maximumLongitude": 7.65,
        "maximumLatitude": 51.5
      }
    }
  },
  {
    "id": "dortmund",
    "name": "Dortmund",
    "aliases": [],
    "latitude": 51.5136,
    "longitude": 7.4653,
    "radiusMeters": 20000,
    "transitRadar": {
      "adapter": "vrrEFA",
      "efaPath": "static03",
      "supportsLiveVehicles": true,
      "radarStops": [
        {
          "id": "20000131",
          "latitude": 51.517198,
          "longitude": 7.459475
        },
        {
          "id": "20000398",
          "latitude": 51.515174,
          "longitude": 7.468494
        },
        {
          "id": "20000526",
          "latitude": 51.510327,
          "longitude": 7.463167
        },
        {
          "id": "20000496",
          "latitude": 51.513737,
          "longitude": 7.454391
        },
        {
          "id": "20000196",
          "latitude": 51.510131,
          "longitude": 7.422582
        },
        {
          "id": "20000228",
          "latitude": 51.488187,
          "longitude": 7.499918
        },
        {
          "id": "20000037",
          "latitude": 51.493165,
          "longitude": 7.556224
        },
        {
          "id": "20000343",
          "latitude": 51.570216,
          "longitude": 7.376255
        },
        {
          "id": "20000204",
          "latitude": 51.493451,
          "longitude": 7.501615
        },
        {
          "id": "20000086",
          "latitude": 51.523564,
          "longitude": 7.546908
        },
        {
          "id": "20000424",
          "latitude": 51.552709,
          "longitude": 7.542857
        }
      ],
      "region": {
        "minimumLongitude": 7.3,
        "minimumLatitude": 51.4,
        "maximumLongitude": 7.65,
        "maximumLatitude": 51.62
      }
    }
  },
  {
    "id": "unna",
    "name": "Unna",
    "aliases": [
      "Kamen",
      "Bergkamen",
      "Lünen",
      "Luenen",
      "Werne",
      "Selm",
      "Bönen",
      "Boenen",
      "Holzwickede",
      "Fröndenberg/Ruhr",
      "Froendenberg/Ruhr",
      "Schwerte"
    ],
    "latitude": 51.5378,
    "longitude": 7.6897,
    "radiusMeters": 30000,
    "transitRadar": {
      "adapter": "ivantoMQTT",
      "agency": "vku",
      "isEnabled": true,
      "region": {
        "minimumLongitude": 7.25,
        "minimumLatitude": 51.3,
        "maximumLongitude": 8.15,
        "maximumLatitude": 51.85
      }
    }
  },
  {
    "id": "neuss",
    "name": "Neuss",
    "aliases": [],
    "latitude": 51.2042,
    "longitude": 6.6879,
    "radiusMeters": 12000,
    "transitRadar": {
      "adapter": "vrrEFA",
      "efaPath": "static03",
      "supportsDepartures": true,
      "supportsLiveVehicles": true,
      "autoRadarStops": true,
      "statusMessage": "Live-Radar (geschätzt) und Live-Abfahrten für Neuss"
    }
  },
  {
    "id": "velbert",
    "name": "Velbert",
    "aliases": [],
    "latitude": 51.3406,
    "longitude": 7.0434,
    "radiusMeters": 12000,
    "transitRadar": [
      {
        "adapter": "dbRegioBusNRW",
        "region": {
          "minimumLongitude": 6.93,
          "minimumLatitude": 51.2,
          "maximumLongitude": 7.3,
          "maximumLatitude": 51.4
        }
      },
      {
        "adapter": "ivantoMQTT",
        "agency": "evag",
        "isEnabled": true,
        "region": {
          "minimumLongitude": 6.72,
          "minimumLatitude": 51.28,
          "maximumLongitude": 7.25,
          "maximumLatitude": 51.58
        }
      },
      {
        "adapter": "vrrEFA",
        "efaPath": "static03",
        "supportsDepartures": true,
        "supportsLiveVehicles": false,
        "statusMessage": "Live-Abfahrten für Velbert"
      }
    ]
  },
  {
    "id": "wesel",
    "name": "Wesel",
    "aliases": [],
    "latitude": 51.6587,
    "longitude": 6.6176,
    "radiusMeters": 14000,
    "transitRadar": [
      {
        "adapter": "dbRegioBusNRW",
        "region": {
          "minimumLongitude": 6.45,
          "minimumLatitude": 51.55,
          "maximumLongitude": 6.8,
          "maximumLatitude": 51.75
        }
      },
      {
        "adapter": "vrrEFA",
        "efaPath": "static03",
        "supportsDepartures": true,
        "supportsLiveVehicles": false,
        "statusMessage": "Live-Abfahrten für Wesel"
      }
    ]
  },
  {
    "id": "grevenbroich",
    "name": "Grevenbroich",
    "aliases": [],
    "latitude": 51.091,
    "longitude": 6.5827,
    "radiusMeters": 14000,
    "transitRadar": {
      "adapter": "dbRegioBusNRW",
      "region": {
        "minimumLongitude": 6.45,
        "minimumLatitude": 51.0,
        "maximumLongitude": 6.75,
        "maximumLatitude": 51.18
      }
    }
  },
  {
    "id": "dormagen",
    "name": "Dormagen",
    "aliases": [],
    "latitude": 51.0937,
    "longitude": 6.842,
    "radiusMeters": 14000,
    "transitRadar": {
      "adapter": "dbRegioBusNRW",
      "region": {
        "minimumLongitude": 6.7,
        "minimumLatitude": 51.0,
        "maximumLongitude": 6.98,
        "maximumLatitude": 51.2
      }
    }
  },
  {
    "id": "viersen",
    "name": "Viersen",
    "aliases": [],
    "latitude": 51.2555,
    "longitude": 6.3965,
    "radiusMeters": 14000,
    "transitRadar": [
      {
        "adapter": "dbRegioBusNRW",
        "region": {
          "minimumLongitude": 6.2,
          "minimumLatitude": 51.15,
          "maximumLongitude": 6.6,
          "maximumLatitude": 51.35
        }
      },
      {
        "adapter": "vrrEFA",
        "efaPath": "static03",
        "supportsDepartures": true,
        "supportsLiveVehicles": false,
        "statusMessage": "Live-Abfahrten für Viersen"
      }
    ]
  },
  {
    "id": "moers",
    "name": "Moers",
    "aliases": [],
    "latitude": 51.4516,
    "longitude": 6.6264,
    "radiusMeters": 16000,
    "transitRadar": {
      "adapter": "vrrEFA",
      "efaPath": "static03",
      "supportsDepartures": true,
      "supportsLiveVehicles": true,
      "autoRadarStops": true,
      "statusMessage": "Live-Radar (geschätzt) und Live-Abfahrten für Moers"
    }
  },
  {
    "id": "moenchengladbach",
    "name": "Mönchengladbach",
    "aliases": [
      "Moenchengladbach"
    ],
    "latitude": 51.1805,
    "longitude": 6.4428,
    "radiusMeters": 18000,
    "transitRadar": {
      "adapter": "vrrEFA",
      "efaPath": "static03",
      "supportsDepartures": true,
      "supportsLiveVehicles": true,
      "autoRadarStops": true,
      "statusMessage": "Live-Radar (geschätzt) und Live-Abfahrten für Mönchengladbach"
    }
  },
  {
    "id": "remscheid",
    "name": "Remscheid",
    "aliases": [],
    "latitude": 51.1787,
    "longitude": 7.1897,
    "radiusMeters": 14000,
    "transitRadar": {
      "adapter": "vrrEFA",
      "efaPath": "static03",
      "supportsDepartures": true,
      "supportsLiveVehicles": true,
      "autoRadarStops": true,
      "statusMessage": "Live-Radar (geschätzt) und Live-Abfahrten für Remscheid"
    }
  },
  {
    "id": "solingen",
    "name": "Solingen",
    "aliases": [],
    "latitude": 51.1652,
    "longitude": 7.0671,
    "radiusMeters": 14000,
    "transitRadar": {
      "adapter": "vrrEFA",
      "efaPath": "static03",
      "supportsDepartures": true,
      "supportsLiveVehicles": true,
      "autoRadarStops": true,
      "statusMessage": "Live-Radar (geschätzt) und Live-Abfahrten für Solingen"
    }
  },
  {
    "id": "munster",
    "name": "Münster",
    "aliases": [
      "Muenster"
    ],
    "latitude": 51.9607,
    "longitude": 7.6261,
    "radiusMeters": 20000,
    "transitRadar": [
      {
        "adapter": "dbRegioBusNRW",
        "region": {
          "minimumLongitude": 7.45,
          "minimumLatitude": 51.83,
          "maximumLongitude": 7.8,
          "maximumLatitude": 52.1
        }
      },
      {
        "adapter": "stadtwerkeMuenster",
        "isEnabled": true
      },
      {
        "adapter": "ivantoMQTT",
        "agency": "wvg",
        "isEnabled": true,
        "region": {
          "minimumLongitude": 7.25,
          "minimumLatitude": 51.65,
          "maximumLongitude": 8.2,
          "maximumLatitude": 52.35
        }
      }
    ]
  },
  {
    "id": "bielefeld",
    "name": "Bielefeld",
    "aliases": [],
    "latitude": 52.0302,
    "longitude": 8.5325,
    "radiusMeters": 18000,
    "transitRadar": {
      "adapter": "dbRegioBusNRW",
      "region": {
        "minimumLongitude": 8.35,
        "minimumLatitude": 51.9,
        "maximumLongitude": 8.75,
        "maximumLatitude": 52.15
      }
    }
  },
  {
    "id": "paderborn",
    "name": "Paderborn",
    "aliases": [],
    "latitude": 51.7189,
    "longitude": 8.7575,
    "radiusMeters": 16000,
    "transitRadar": {
      "adapter": "dbRegioBusNRW",
      "region": {
        "minimumLongitude": 8.55,
        "minimumLatitude": 51.6,
        "maximumLongitude": 8.95,
        "maximumLatitude": 51.85
      }
    }
  },
  {
    "id": "schaumburg",
    "name": "Schaumburg",
    "aliases": [
      "Stadthagen",
      "Bückeburg",
      "Bueckeburg",
      "Rinteln",
      "Bad Nenndorf",
      "Obernkirchen",
      "Nienstädt",
      "Nienstaedt",
      "Lindhorst",
      "Rodenberg",
      "Auetal",
      "Hagenburg",
      "Lauenau"
    ],
    "latitude": 52.3232,
    "longitude": 9.2032,
    "radiusMeters": 45000,
    "transitRadar": {
      "adapter": "shgMobil",
      "isEnabled": true
    }
  },
  {
    "id": "frankfurt-am-main",
    "name": "Frankfurt am Main",
    "aliases": [
      "Frankfurt"
    ],
    "latitude": 50.1109,
    "longitude": 8.6821,
    "radiusMeters": 18000,
    "transitRadar": {"adapter":"rmvHafas","isEnabled":true,"supportsDepartures":true,"supportsLiveVehicles":false,"supportsRealtimeDelay":true,"statusMessage":"RMV-Abfahrten"}
  },
  {
    "id": "freising",
    "name": "Freising",
    "aliases": [],
    "latitude": 48.402,
    "longitude": 11.749,
    "radiusMeters": 14000,
    "transitRadar": {
      "adapter": "mvvEFA",
      "efaPath": "ng",
      "supportsCoordinateCatalog": false,
      "supportsLiveVehicles": true,
      "radarStops": [
        {
          "id": "1002680",
          "latitude": 48.3964,
          "longitude": 11.7432
        }
      ],
      "region": {
        "minimumLongitude": 11.64,
        "minimumLatitude": 48.29,
        "maximumLongitude": 11.85,
        "maximumLatitude": 48.5
      }
    }
  },
  {
    "id": "karlsruhe-08212000",
    "name": "Karlsruhe",
    "aliases": [],
    "latitude": 49.0069,
    "longitude": 8.4037,
    "radiusMeters": 18000,
    "transitRadar": {
      "adapter": "kvvEFA",
      "efaPath": "sl3-alone",
      "supportsLiveVehicles": true,
      "radarStops": [
        {
          "id": "7000090",
          "latitude": 48.993349,
          "longitude": 8.401036
        },
        {
          "id": "7000089",
          "latitude": 48.994369,
          "longitude": 8.39967
        },
        {
          "id": "7000088",
          "latitude": 48.991746,
          "longitude": 8.40126
        },
        {
          "id": "7001003",
          "latitude": 49.009656,
          "longitude": 8.402383
        },
        {
          "id": "7000037",
          "latitude": 49.009827,
          "longitude": 8.394873
        },
        {
          "id": "7000003",
          "latitude": 49.00909,
          "longitude": 8.417834
        },
        {
          "id": "7000039",
          "latitude": 49.010705,
          "longitude": 8.384246
        },
        {
          "id": "7000071",
          "latitude": 49.005455,
          "longitude": 8.40223
        },
        {
          "id": "7000080",
          "latitude": 49.008855,
          "longitude": 8.410073
        },
        {
          "id": "7000065",
          "latitude": 48.999385,
          "longitude": 8.385998
        },
        {
          "id": "7000402",
          "latitude": 49.013792,
          "longitude": 8.430464
        }
      ],
      "region": {
        "minimumLongitude": 8.25,
        "minimumLatitude": 48.92,
        "maximumLongitude": 8.55,
        "maximumLatitude": 49.1
      }
    }
  },
  {
    "id": "rastatt-08216043",
    "name": "Rastatt",
    "aliases": [],
    "latitude": 48.8572,
    "longitude": 8.203,
    "radiusMeters": 14000,
    "transitRadar": {
      "adapter": "kvvEFA",
      "efaPath": "sl3-alone",
      "supportsLiveVehicles": true,
      "radarStops": [
        {
          "id": "7001844",
          "latitude": 48.860593,
          "longitude": 8.215246
        },
        {
          "id": "7001845",
          "latitude": 48.861645,
          "longitude": 8.215947
        },
        {
          "id": "7032021",
          "latitude": 48.858211,
          "longitude": 8.208024
        },
        {
          "id": "7033113",
          "latitude": 48.857437,
          "longitude": 8.202589
        },
        {
          "id": "7034664",
          "latitude": 48.866609,
          "longitude": 8.224076
        },
        {
          "id": "7031994",
          "latitude": 48.852005,
          "longitude": 8.225172
        },
        {
          "id": "7034653",
          "latitude": 48.875165,
          "longitude": 8.189366
        },
        {
          "id": "7031877",
          "latitude": 48.838113,
          "longitude": 8.203101
        }
      ],
      "region": {
        "minimumLongitude": 8.1,
        "minimumLatitude": 48.78,
        "maximumLongitude": 8.35,
        "maximumLatitude": 48.94
      }
    }
  },
  {
    "id": "ettlingen-08215017",
    "name": "Ettlingen",
    "aliases": [],
    "latitude": 48.9409,
    "longitude": 8.4072,
    "radiusMeters": 12000,
    "transitRadar": {
      "adapter": "kvvEFA",
      "efaPath": "sl3-alone",
      "supportsLiveVehicles": true,
      "radarStops": [
        {
          "id": "7001231",
          "latitude": 48.938691,
          "longitude": 8.40895
        },
        {
          "id": "7001840",
          "latitude": 48.947129,
          "longitude": 8.387866
        },
        {
          "id": "7001223",
          "latitude": 48.940703,
          "longitude": 8.404548
        },
        {
          "id": "7001221",
          "latitude": 48.945247,
          "longitude": 8.398745
        },
        {
          "id": "7001235",
          "latitude": 48.936791,
          "longitude": 8.415534
        },
        {
          "id": "7037212",
          "latitude": 48.942362,
          "longitude": 8.406416
        },
        {
          "id": "7008204",
          "latitude": 48.924197,
          "longitude": 8.374634
        },
        {
          "id": "7001237",
          "latitude": 48.934555,
          "longitude": 8.442232
        }
      ],
      "region": {
        "minimumLongitude": 8.3,
        "minimumLatitude": 48.86,
        "maximumLongitude": 8.52,
        "maximumLatitude": 49.0
      }
    }
  },
  {
    "id": "bruchsal-08215009",
    "name": "Bruchsal",
    "aliases": [],
    "latitude": 49.1243,
    "longitude": 8.598,
    "radiusMeters": 14000,
    "transitRadar": {
      "adapter": "kvvEFA",
      "efaPath": "sl3-alone",
      "supportsLiveVehicles": true,
      "radarStops": [
        {
          "id": "7001856",
          "latitude": 49.124924,
          "longitude": 8.590347
        },
        {
          "id": "7012616",
          "latitude": 49.123678,
          "longitude": 8.60101
        },
        {
          "id": "7012626",
          "latitude": 49.125753,
          "longitude": 8.593464
        },
        {
          "id": "7001857",
          "latitude": 49.13139,
          "longitude": 8.594092
        },
        {
          "id": "7001855",
          "latitude": 49.110395,
          "longitude": 8.574563
        },
        {
          "id": "7012659",
          "latitude": 49.133212,
          "longitude": 8.604046
        },
        {
          "id": "7012667",
          "latitude": 49.117534,
          "longitude": 8.566712
        },
        {
          "id": "7032274",
          "latitude": 49.086656,
          "longitude": 8.549536
        }
      ],
      "region": {
        "minimumLongitude": 8.48,
        "minimumLatitude": 49.04,
        "maximumLongitude": 8.72,
        "maximumLatitude": 49.2
      }
    }
  },
  {
    "id": "stuttgart",
    "name": "Stuttgart",
    "aliases": [],
    "latitude": 48.7758,
    "longitude": 9.1829,
    "radiusMeters": 18000,
    "transitRadar": {
      "adapter": "vvsEFA",
      "efaPath": "mngvvs",
      "supportsLiveVehicles": true,
      "radarStops": [
        {
          "id": "5006118",
          "latitude": 48.783386,
          "longitude": 9.180229
        },
        {
          "id": "5006115",
          "latitude": 48.784731,
          "longitude": 9.183173
        },
        {
          "id": "5006112",
          "latitude": 48.78316,
          "longitude": 9.181126
        },
        {
          "id": "5006075",
          "latitude": 48.776278,
          "longitude": 9.182911
        },
        {
          "id": "5006333",
          "latitude": 48.80128,
          "longitude": 9.217469
        },
        {
          "id": "5006002",
          "latitude": 48.726981,
          "longitude": 9.113913
        },
        {
          "id": "5000107",
          "latitude": 48.832229,
          "longitude": 9.170598
        }
      ],
      "region": {
        "minimumLongitude": 8.95,
        "minimumLatitude": 48.65,
        "maximumLongitude": 9.35,
        "maximumLatitude": 48.9
      }
    }
  },
  {
    "id": "esslingen-am-neckar-08116019",
    "name": "Esslingen am Neckar",
    "aliases": [
      "Esslingen"
    ],
    "latitude": 48.74,
    "longitude": 9.31,
    "radiusMeters": 12000,
    "transitRadar": {
      "adapter": "vvsEFA",
      "efaPath": "mngvvs",
      "supportsLiveVehicles": true,
      "radarStops": [
        {
          "id": "5007801",
          "latitude": 48.738872,
          "longitude": 9.301369
        },
        {
          "id": "5007800",
          "latitude": 48.738541,
          "longitude": 9.300578
        },
        {
          "id": "5004034",
          "latitude": 48.743384,
          "longitude": 9.30576
        },
        {
          "id": "5001802",
          "latitude": 48.729836,
          "longitude": 9.327277
        },
        {
          "id": "5006763",
          "latitude": 48.738062,
          "longitude": 9.327848
        },
        {
          "id": "5001803",
          "latitude": 48.724361,
          "longitude": 9.35974
        },
        {
          "id": "5004148",
          "latitude": 48.718494,
          "longitude": 9.31837
        },
        {
          "id": "5003993",
          "latitude": 48.74789,
          "longitude": 9.277028
        },
        {
          "id": "5005021",
          "latitude": 48.715483,
          "longitude": 9.29423
        }
      ],
      "region": {
        "minimumLongitude": 9.2,
        "minimumLatitude": 48.66,
        "maximumLongitude": 9.42,
        "maximumLatitude": 48.81
      }
    }
  },
  {
    "id": "boeblingen-08115003",
    "name": "Böblingen",
    "aliases": [
      "Boeblingen"
    ],
    "latitude": 48.685,
    "longitude": 9.012,
    "radiusMeters": 12000,
    "transitRadar": {
      "adapter": "vvsEFA",
      "efaPath": "mngvvs",
      "supportsLiveVehicles": true,
      "radarStops": [
        {
          "id": "5007100",
          "latitude": 48.687849,
          "longitude": 9.004532
        }
      ],
      "region": {
        "minimumLongitude": 8.9,
        "minimumLatitude": 48.6,
        "maximumLongitude": 9.15,
        "maximumLatitude": 48.77
      }
    }
  },
  {
    "id": "ludwigsburg-08118048",
    "name": "Ludwigsburg",
    "aliases": [],
    "latitude": 48.897,
    "longitude": 9.192,
    "radiusMeters": 12000,
    "transitRadar": {
      "adapter": "vvsEFA",
      "efaPath": "mngvvs",
      "supportsLiveVehicles": true,
      "radarStops": [
        {
          "id": "5007402",
          "latitude": 48.892086,
          "longitude": 9.18523
        }
      ],
      "region": {
        "minimumLongitude": 9.07,
        "minimumLatitude": 48.81,
        "maximumLongitude": 9.33,
        "maximumLatitude": 48.98
      }
    }
  },
  {
    "id": "waiblingen-08119079",
    "name": "Waiblingen",
    "aliases": [],
    "latitude": 48.83,
    "longitude": 9.316,
    "radiusMeters": 12000,
    "transitRadar": {
      "adapter": "vvsEFA",
      "efaPath": "mngvvs",
      "supportsLiveVehicles": true,
      "radarStops": [
        {
          "id": "5007604",
          "latitude": 48.826244,
          "longitude": 9.300477
        }
      ],
      "region": {
        "minimumLongitude": 9.2,
        "minimumLatitude": 48.74,
        "maximumLongitude": 9.43,
        "maximumLatitude": 48.91
      }
    }
  },
  {
    "id": "ulm",
    "name": "Ulm",
    "aliases": [
      "Neu-Ulm",
      "Neu Ulm"
    ],
    "latitude": 48.4011,
    "longitude": 9.9876,
    "radiusMeters": 20000,
    "transitRadar": {
      "adapter": "swu",
      "isEnabled": true
    }
  },
  {
    "id": "dresden",
    "name": "Dresden",
    "aliases": [],
    "latitude": 51.0504,
    "longitude": 13.7373,
    "radiusMeters": 20000,
    "transitRadar": {
      "adapter": "vvo",
      "providerID": "vvo-dresden",
      "efaPath": "vvo",
      "isEnabled": true,
      "isExperimental": true,
      "supportsLiveVehicles": true,
      "supportsRealtimeDelay": true,
      "statusMessage": "Live-Radar und Live-Abfahrten für Dresden",
      "region": {
        "minimumLongitude": 13.5,
        "minimumLatitude": 50.8,
        "maximumLongitude": 14.0,
        "maximumLatitude": 51.3
      }
    }
  },
  {
    "id": "pirna",
    "name": "Pirna",
    "aliases": [],
    "latitude": 50.9584,
    "longitude": 13.9402,
    "radiusMeters": 12000,
    "transitRadar": {
      "adapter": "vvo",
      "providerID": "vvo-pirna",
      "efaPath": "vvo",
      "isEnabled": true,
      "isExperimental": true,
      "supportsLiveVehicles": true,
      "supportsRealtimeDelay": true,
      "statusMessage": "Live-Radar und Live-Abfahrten für Pirna",
      "region": {
        "minimumLongitude": 13.8,
        "minimumLatitude": 50.86,
        "maximumLongitude": 14.08,
        "maximumLatitude": 51.05
      }
    }
  },
  {
    "id": "meissen",
    "name": "Meißen",
    "aliases": [
      "Meissen"
    ],
    "latitude": 51.1645,
    "longitude": 13.4697,
    "radiusMeters": 12000,
    "transitRadar": {
      "adapter": "vvo",
      "providerID": "vvo-meissen",
      "efaPath": "vvo",
      "isEnabled": true,
      "isExperimental": true,
      "supportsLiveVehicles": true,
      "supportsRealtimeDelay": true,
      "statusMessage": "Live-Radar und Live-Abfahrten für Meißen",
      "region": {
        "minimumLongitude": 13.25,
        "minimumLatitude": 51.05,
        "maximumLongitude": 13.65,
        "maximumLatitude": 51.24
      }
    }
  },
  {"id":"bad-homburg-vor-der-hohe","name":"Bad Homburg vor der Höhe","aliases":["Bad Homburg"],"latitude":50.226,"longitude":8.619,"radiusMeters":18000,"transitRadar":{"adapter":"rmvHafas","isEnabled":true,"supportsDepartures":true,"supportsLiveVehicles":false,"supportsRealtimeDelay":true,"statusMessage":"RMV-Abfahrten"}},
  {"id":"fulda","name":"Fulda","aliases":[],"latitude":50.5558,"longitude":9.6808,"radiusMeters":18000,"transitRadar":{"adapter":"rmvHafas","isEnabled":true,"supportsDepartures":true,"supportsLiveVehicles":false,"supportsRealtimeDelay":true,"statusMessage":"RMV-Abfahrten"}},
  {"id":"giessen","name":"Gießen","aliases":["Giessen"],"latitude":50.5841,"longitude":8.6784,"radiusMeters":18000,"transitRadar":{"adapter":"rmvHafas","isEnabled":true,"supportsDepartures":true,"supportsLiveVehicles":false,"supportsRealtimeDelay":true,"statusMessage":"RMV-Abfahrten"}},
  {"id":"hanau","name":"Hanau","aliases":[],"latitude":50.1269,"longitude":8.928,"radiusMeters":18000,"transitRadar":{"adapter":"rmvHafas","isEnabled":true,"supportsDepartures":true,"supportsLiveVehicles":false,"supportsRealtimeDelay":true,"statusMessage":"RMV-Abfahrten"}},
  {"id":"marburg","name":"Marburg","aliases":[],"latitude":50.807,"longitude":8.7705,"radiusMeters":18000,"transitRadar":{"adapter":"rmvHafas","isEnabled":true,"supportsDepartures":true,"supportsLiveVehicles":false,"supportsRealtimeDelay":true,"statusMessage":"RMV-Abfahrten"}},
  {"id":"offenbach-am-main","name":"Offenbach am Main","aliases":["Offenbach"],"latitude":50.0956,"longitude":8.7761,"radiusMeters":18000,"transitRadar":{"adapter":"rmvHafas","isEnabled":true,"supportsDepartures":true,"supportsLiveVehicles":false,"supportsRealtimeDelay":true,"statusMessage":"RMV-Abfahrten"}},
  {"id":"ruesselsheim-am-main","name":"Rüsselsheim am Main","aliases":["Ruesselsheim","Rüsselsheim"],"latitude":49.9896,"longitude":8.4227,"radiusMeters":18000,"transitRadar":{"adapter":"rmvHafas","isEnabled":true,"supportsDepartures":true,"supportsLiveVehicles":false,"supportsRealtimeDelay":true,"statusMessage":"RMV-Abfahrten"}},
  {"id":"wiesbaden","name":"Wiesbaden","aliases":[],"latitude":50.0782,"longitude":8.2398,"radiusMeters":18000,"transitRadar":{"adapter":"rmvHafas","isEnabled":true,"supportsDepartures":true,"supportsLiveVehicles":false,"supportsRealtimeDelay":true,"statusMessage":"RMV-Abfahrten"}},
  {"id":"amsterdam","name":"Amsterdam","aliases":[],"latitude":52.3676,"longitude":4.9041,"radiusMeters":20000,"transitRadar":{"adapter":"netherlands","isEnabled":true,"supportsDepartures":true,"supportsLiveVehicles":true,"supportsRealtimeDelay":true,"statusMessage":"Live-Radar und Live-Abfahrten für Amsterdam"}},
  {"id":"rotterdam","name":"Rotterdam","aliases":[],"latitude":51.9244,"longitude":4.4777,"radiusMeters":20000,"transitRadar":{"adapter":"netherlands","isEnabled":true,"supportsDepartures":true,"supportsLiveVehicles":true,"supportsRealtimeDelay":true,"statusMessage":"Live-Radar und Live-Abfahrten für Rotterdam"}},
  {"id":"utrecht","name":"Utrecht","aliases":[],"latitude":52.0907,"longitude":5.1214,"radiusMeters":18000,"transitRadar":{"adapter":"netherlands","isEnabled":true,"supportsDepartures":true,"supportsLiveVehicles":true,"supportsRealtimeDelay":true,"statusMessage":"Live-Radar und Live-Abfahrten für Utrecht"}},
  {"id":"den-haag","name":"Den Haag","aliases":["The Hague","'s-Gravenhage"],"latitude":52.0705,"longitude":4.3007,"radiusMeters":18000,"transitRadar":{"adapter":"netherlands","isEnabled":true,"supportsDepartures":true,"supportsLiveVehicles":true,"supportsRealtimeDelay":true,"statusMessage":"Live-Radar und Live-Abfahrten für Den Haag"}},
  {"id":"eindhoven","name":"Eindhoven","aliases":[],"latitude":51.4416,"longitude":5.4697,"radiusMeters":18000,"transitRadar":{"adapter":"netherlands","isEnabled":true,"supportsDepartures":true,"supportsLiveVehicles":true,"supportsRealtimeDelay":true,"statusMessage":"Live-Radar und Live-Abfahrten für Eindhoven"}},
  {"id":"groningen","name":"Groningen","aliases":[],"latitude":53.2194,"longitude":6.5665,"radiusMeters":18000,"transitRadar":{"adapter":"netherlands","isEnabled":true,"supportsDepartures":true,"supportsLiveVehicles":true,"supportsRealtimeDelay":true,"statusMessage":"Live-Radar und Live-Abfahrten für Groningen"}},
  {"id":"maastricht","name":"Maastricht","aliases":[],"latitude":50.8514,"longitude":5.6910,"radiusMeters":15000,"transitRadar":{"adapter":"netherlands","isEnabled":true,"supportsDepartures":true,"supportsLiveVehicles":true,"supportsRealtimeDelay":true,"statusMessage":"Live-Radar und Live-Abfahrten für Maastricht"}}
]
